{
  "id": "tnr_1756070925286",
  "name": "rec_1756070925286",
  "description": "",
  "tags": [],
  "createdAt": "2025-08-24T21:32:58.781Z",
  "config": {
    "url": ""
  },
  "sessions": [],
  "events": [
    {
      "t": 14,
      "cpId": "sim-1756071088927-rrnv",
      "dir": "ui",
      "action": "meter:MeterValues",
      "payload": {
        "powerActiveKw": 7.63,
        "powerOfferedKw": 7.36
      }
    },
    {
      "t": 1924,
      "cpId": "sim-1756071088927-rrnv",
      "dir": "ui",
      "action": "meter:MeterValues",
      "payload": {
        "powerActiveKw": 7.63,
        "powerOfferedKw": 7.36
      }
    },
    {
      "t": 2330,
      "cpId": "sim-1756071088927-rrnv",
      "dir": "ui",
      "action": "session:DISCONNECT",
      "payload": {
        "id": "sim-1756071088927-rrnv"
      }
    }
  ],
  "metadata": {
    "name": "rec_1756070925286",
    "description": "",
    "tags": [],
    "config": {
      "url": ""
    },
    "startedAt": "2025-08-24T21:32:53.016Z",
    "url": "",
    "endedAt": "2025-08-24T21:32:58.781Z",
    "durationMs": 5765
  },
  "expected": {}
}