{
  "executionId": "exec_1755808081039_bbg9",
  "scenarioId": "tnr_1755807981088",
  "startedAt": "2025-08-21T20:28:01.039Z",
  "status": "error",
  "events": [],
  "serverCalls": [],
  "differences": [],
  "logs": [
    {
      "ts": "22:28:01",
      "line": "🚀 Starting replay of scenario: rec_1755807981088"
    },
    {
      "ts": "22:28:01",
      "line": "❌ Replay error: No URL in scenario config"
    }
  ],
  "error": "No URL in scenario config",
  "passed": false,
  "finishedAt": "2025-08-21T20:28:01.040Z",
  "metrics": {
    "totalEvents": 0,
    "differences": 0,
    "duration": 1
  }
}